kchatdriver/__init__.py
kchatdriver/client.py
kchatdriver/driver.py
kchatdriver/exceptions.py
kchatdriver/version.py
kchatdriver/websocket.py
kchatdriver/endpoints/__init__.py
kchatdriver/endpoints/base.py
kchatdriver/endpoints/bots.py
kchatdriver/endpoints/channels.py
kchatdriver/endpoints/commands.py
kchatdriver/endpoints/emoji.py
kchatdriver/endpoints/files.py
kchatdriver/endpoints/integration_actions.py
kchatdriver/endpoints/posts.py
kchatdriver/endpoints/preferences.py
kchatdriver/endpoints/reactions.py
kchatdriver/endpoints/roles.py
kchatdriver/endpoints/scheme.py
kchatdriver/endpoints/status.py
kchatdriver/endpoints/system.py
kchatdriver/endpoints/teams.py
kchatdriver/endpoints/users.py
kchatdriver/endpoints/webhooks.py
kchatdriver-0.1.1.dist-info/LICENSE
kchatdriver-0.1.1.dist-info/METADATA
kchatdriver-0.1.1.dist-info/WHEEL
kchatdriver-0.1.1.dist-info/top_level.txt
kchatdriver-0.1.1.dist-info/RECORD
