Metadata-Version: 2.1
Name: kchatdriver
Version: 0.1.1
Summary: A Python kChat Driver
Home-page: https://github.com/infomaniak/python-kchat-driver
Author: Léopold Jacquot
Author-email: leopold.jacquot@gmail.com
License: MIT
Platform: UNKNOWN
Classifier: Environment :: Web Environment
Classifier: Intended Audience :: Developers
Classifier: Programming Language :: Python
Classifier: Programming Language :: Python :: 3
Classifier: Programming Language :: Python :: 3.7
Classifier: Programming Language :: Python :: 3.8
Classifier: Programming Language :: Python :: 3.9
Classifier: Programming Language :: Python :: 3.10
Classifier: Programming Language :: Python :: 3.11
Requires-Python: >=3.7
License-File: LICENSE
Requires-Dist: requests~=2.27.1
Requires-Dist: pusher~=3.3.0
Requires-Dist: infomaniakpysher~=0.0.1
